short_poetry/__init__.py
short_poetry-0.1.0.dist-info/METADATA
short_poetry-0.1.0.dist-info/WHEEL
short_poetry-0.1.0.dist-info/RECORD
