Metadata-Version: 2.1
Name: short-poetry
Version: 0.1.0
Summary: 
Author: Wesley Lira
Author-email: wesleeylirac12@gmail.com
Requires-Python: >=3.10,<4.0
Classifier: Programming Language :: Python :: 3
Classifier: Programming Language :: Python :: 3.10
Classifier: Programming Language :: Python :: 3.11
Requires-Dist: Babel (>=2.10.3,<3.0.0)
Requires-Dist: GitPython (>=3.1.27,<4.0.0)
Requires-Dist: Jinja2 (>=3.1.2,<4.0.0)
Requires-Dist: Markdown (>=3.3.7,<4.0.0)
Requires-Dist: MarkupSafe (>=2.1.1,<3.0.0)
Requires-Dist: Pillow (>=9.1.1,<10.0.0)
Requires-Dist: PyYAML (>=6.0,<7.0)
Requires-Dist: Pygments (>=2.12.0,<3.0.0)
Requires-Dist: Sphinx (>=5.0.2,<6.0.0)
Requires-Dist: Werkzeug (>=2.1.2,<3.0.0)
Requires-Dist: absl-py (>=1.1.0,<2.0.0)
Requires-Dist: alabaster (>=0.7.12,<0.8.0)
Requires-Dist: autopep8 (>=1.6.0,<2.0.0)
Requires-Dist: cachetools (>=5.2.0,<6.0.0)
Requires-Dist: certifi (>=2022.5.18.1,<2023.0.0.0)
Requires-Dist: charset-normalizer (>=2.0.12,<3.0.0)
Requires-Dist: click (>=8.1.3,<9.0.0)
Requires-Dist: cycler (>=0.11.0,<0.12.0)
Requires-Dist: dglgo (>=0.0.1,<0.0.2)
Requires-Dist: docker-pycreds (>=0.4.0,<0.5.0)
Requires-Dist: docutils (>=0.18.1,<0.19.0)
Requires-Dist: filelock (>=3.7.1,<4.0.0)
Requires-Dist: fonttools (>=4.33.3,<5.0.0)
Requires-Dist: gensim (>=4.2.0,<5.0.0)
Requires-Dist: gitdb (>=4.0.9,<5.0.0)
Requires-Dist: google-auth (>=2.8.0,<3.0.0)
Requires-Dist: google-auth-oauthlib (>=0.4.6,<0.5.0)
Requires-Dist: grpcio (>=1.47.0,<2.0.0)
Requires-Dist: huggingface-hub (>=0.9.1,<0.10.0)
Requires-Dist: idna (>=3.3,<4.0)
Requires-Dist: imagesize (>=1.4.1,<2.0.0)
Requires-Dist: importlib-metadata (>=4.11.4,<5.0.0)
Requires-Dist: isort (>=5.10.1,<6.0.0)
Requires-Dist: joblib (>=1.1.0,<2.0.0)
Requires-Dist: kiwisolver (>=1.4.2,<2.0.0)
Requires-Dist: matplotlib (>=3.5.2,<4.0.0)
Requires-Dist: networkx (>=2.8.4,<3.0.0)
Requires-Dist: nltk (>=3.7,<4.0)
Requires-Dist: numpy (>=1.23.0,<2.0.0)
Requires-Dist: numpydoc (>=1.4.0,<2.0.0)
Requires-Dist: oauthlib (>=3.2.0,<4.0.0)
Requires-Dist: packaging (>=21.3,<22.0)
Requires-Dist: pandas (>=1.4.4,<2.0.0)
Requires-Dist: pathtools (>=0.1.2,<0.2.0)
Requires-Dist: promise (>=2.3,<3.0)
Requires-Dist: protobuf (>=3.19.4,<4.0.0)
Requires-Dist: psutil (>=5.9.1,<6.0.0)
Requires-Dist: pyasn1 (>=0.4.8,<0.5.0)
Requires-Dist: pyasn1-modules (>=0.2.8,<0.3.0)
Requires-Dist: pycodestyle (>=2.8.0,<3.0.0)
Requires-Dist: pydantic (>=1.9.1,<2.0.0)
Requires-Dist: pyparsing (>=3.0.9,<4.0.0)
Requires-Dist: python-dateutil (>=2.8.2,<3.0.0)
Requires-Dist: pytz (>=2022.1,<2023.0)
Requires-Dist: regex (>=2022.6.2,<2023.0.0)
Requires-Dist: requests (>=2.28.0,<3.0.0)
Requires-Dist: requests-oauthlib (>=1.3.1,<2.0.0)
Requires-Dist: rsa (>=4.8,<5.0)
Requires-Dist: ruamel-yaml (>=0.17.32,<0.18.0)
Requires-Dist: scikit-learn (>=1.1.1,<2.0.0)
Requires-Dist: scipy (>=1.8.1,<2.0.0)
Requires-Dist: sentry-sdk (>=1.6.0,<2.0.0)
Requires-Dist: setproctitle (>=1.2.3,<2.0.0)
Requires-Dist: shortuuid (>=1.0.9,<2.0.0)
Requires-Dist: six (>=1.16.0,<2.0.0)
Requires-Dist: smart-open (>=6.0.0,<7.0.0)
Requires-Dist: smmap (>=5.0.0,<6.0.0)
Requires-Dist: snowballstemmer (>=2.2.0,<3.0.0)
Requires-Dist: sphinxcontrib-applehelp (>=1.0.2,<2.0.0)
Requires-Dist: sphinxcontrib-devhelp (>=1.0.2,<2.0.0)
Requires-Dist: sphinxcontrib-htmlhelp (>=2.0.0,<3.0.0)
Requires-Dist: sphinxcontrib-jsmath (>=1.0.1,<2.0.0)
Requires-Dist: sphinxcontrib-qthelp (>=1.0.3,<2.0.0)
Requires-Dist: sphinxcontrib-serializinghtml (>=1.1.5,<2.0.0)
Requires-Dist: tensorboard (>=2.9.1,<3.0.0)
Requires-Dist: tensorboard-data-server (>=0.6.1,<0.7.0)
Requires-Dist: tensorboard-plugin-wit (>=1.8.1,<2.0.0)
Requires-Dist: threadpoolctl (>=3.1.0,<4.0.0)
Requires-Dist: tokenizers (>=0.12.1,<0.13.0)
Requires-Dist: toml (>=0.10.2,<0.11.0)
Requires-Dist: torch (>=1.11.0,<2.0.0)
Requires-Dist: tqdm (>=4.64.0,<5.0.0)
Requires-Dist: transformers (>=4.22.0,<5.0.0)
Requires-Dist: typer (>=0.4.1,<0.5.0)
Requires-Dist: typing-extensions (>=4.2.0,<5.0.0)
Requires-Dist: urllib3 (>=1.26.9,<2.0.0)
Requires-Dist: wandb (>=0.12.20,<0.13.0)
Requires-Dist: zipp (>=3.8.0,<4.0.0)
